[
  {"name": "Product 1", "price": 343},
  {"name": "Product 2", "price": 152},
  {"name": "Product 3", "price": 121},
  {"name": "Product 4", "price": 646},
  {"name": "Product 5", "price": 698},
  {"name": "Product 6", "price": 192},
  {"name": "Product 7", "price": 536},
  {"name": "Product 8", "price": 321},
  {"name": "Product 9", "price": 384},
  {"name": "Product 10", "price": 175},
  {"name": "Product 11", "price": 669},
  {"name": "Product 12", "price": 361},
  {"name": "Product 13", "price": 975},
  {"name": "Product 14", "price": 314},
  {"name": "Product 15", "price": 334},
  {"name": "Product 16", "price": 625},
  {"name": "Product 17", "price": 531},
  {"name": "Product 18", "price": 657},
  {"name": "Product 19", "price": 65},
  {"name": "Product 20", "price": 578},
  {"name": "Product 21", "price": 565},
  {"name": "Product 22", "price": 648},
  {"name": "Product 23", "price": 584},
  {"name": "Product 24", "price": 239},
  {"name": "Product 25", "price": 756},
  {"name": "Product 26", "price": 294},
  {"name": "Product 27", "price": 550},
  {"name": "Product 28", "price": 604},
  {"name": "Product 29", "price": 159},
  {"name": "Product 30", "price": 424},
  {"name": "Product 31", "price": 783},
  {"name": "Product 32", "price": 333},
  {"name": "Product 33", "price": 852},
  {"name": "Product 34", "price": 646},
  {"name": "Product 35", "price": 142},
  {"name": "Product 36", "price": 107},
  {"name": "Product 37", "price": 895},
  {"name": "Product 38", "price": 188},
  {"name": "Product 39", "price": 809},
  {"name": "Product 40", "price": 906},
  {"name": "Product 41", "price": 375},
  {"name": "Product 42", "price": 784},
  {"name": "Product 43", "price": 154},
  {"name": "Product 44", "price": 872},
  {"name": "Product 45", "price": 288},
  {"name": "Product 46", "price": 906},
  {"name": "Product 47", "price": 672},
  {"name": "Product 48", "price": 465},
  {"name": "Product 49", "price": 32},
  {"name": "Product 50", "price": 607}
]
